chatgpt/__init__.py
chatgpt/run.py
chatgpt/src/__init__.py
chatgpt/src/bot.py
chatgpt/src/bot_exceptions.py
chatgpt/src/utils.py
pybot_chatgpt-2.0.0.dist-info/LICENSE
pybot_chatgpt-2.0.0.dist-info/METADATA
pybot_chatgpt-2.0.0.dist-info/WHEEL
pybot_chatgpt-2.0.0.dist-info/entry_points.txt
pybot_chatgpt-2.0.0.dist-info/top_level.txt
pybot_chatgpt-2.0.0.dist-info/RECORD
