Metadata-Version: 2.1
Name: pybot-chatgpt
Version: 2.0.0
Summary: PythonBot wrapping ChatGPT API
Home-page: https://github.com/shubhamraj2202/pybot-chatgpt
Author: Shubham Raj
Author-email: shubhamraj2202@gmail.com
Project-URL: Bug Reports, https://github.com/shubhamraj2202/pybot-chatgpt/issues
License-File: LICENSE
Requires-Dist: openai
